abstract_dataloader/__init__.py
abstract_dataloader/abstract.py
abstract_dataloader/py.typed
abstract_dataloader/spec.py
abstract_dataloader/ext/__init__.py
abstract_dataloader/ext/augment.py
abstract_dataloader/ext/graph.py
abstract_dataloader/ext/lightning.py
abstract_dataloader/ext/objective.py
abstract_dataloader/ext/sample.py
abstract_dataloader/ext/torch.py
abstract_dataloader/ext/types.py
abstract_dataloader/generic/__init__.py
abstract_dataloader/generic/composition.py
abstract_dataloader/generic/sequence.py
abstract_dataloader/generic/sync.py
abstract_dataloader-0.4.6.dist-info/METADATA
abstract_dataloader-0.4.6.dist-info/WHEEL
abstract_dataloader-0.4.6.dist-info/licenses/LICENSE
abstract_dataloader-0.4.6.dist-info/RECORD
