Metadata-Version: 2.4
Name: abstract_dataloader
Version: 0.4.6
Summary: Abstract Dataloader: Dataloader Not Included.
Project-URL: Homepage, https://github.com/RadarML/abstract-dataloader
Project-URL: Documentation, https://radarml.github.io/abstract-dataloader/
Project-URL: Issues, https://github.com/RadarML/abstract-dataloader/issues
Author-email: Tianshu Huang <tianshu2@andrew.cmu.edu>
License-Expression: MIT
License-File: LICENSE
Classifier: Operating System :: OS Independent
Classifier: Programming Language :: Python :: 3.10
Classifier: Programming Language :: Python :: 3.11
Classifier: Programming Language :: Python :: 3.12
Classifier: Programming Language :: Python :: 3.13
Classifier: Typing :: Typed
Requires-Python: >=3.10
Requires-Dist: jaxtyping>=0.2.32
Requires-Dist: numpy>=1.14
Requires-Dist: optree>=0.16
Requires-Dist: typing-extensions>=3.12
Requires-Dist: wadler-lindig>=0.1.3
Provides-Extra: dev
Requires-Dist: beartype>=0.20.0; extra == 'dev'
Requires-Dist: coverage; extra == 'dev'
Requires-Dist: lightning>=2.0.0; extra == 'dev'
Requires-Dist: pre-commit>=4.0.0; extra == 'dev'
Requires-Dist: pyright>=1.0.0; extra == 'dev'
Requires-Dist: pytest; extra == 'dev'
Requires-Dist: pytest-cov; extra == 'dev'
Requires-Dist: ruff>=0.10.0; extra == 'dev'
Requires-Dist: torch>=2.2; extra == 'dev'
Provides-Extra: docs
Requires-Dist: griffe==1.8.0; extra == 'docs'
Requires-Dist: mkdocs-material==9.6.*; extra == 'docs'
Requires-Dist: mkdocs==1.6.*; extra == 'docs'
Requires-Dist: mkdocstrings-python-xref==1.16.3; extra == 'docs'
Requires-Dist: mkdocstrings-python==1.16.6; extra == 'docs'
Requires-Dist: mkdocstrings==0.29.*; extra == 'docs'
Requires-Dist: ruff>=0.10.0; extra == 'docs'
Provides-Extra: torch
Requires-Dist: optree>=0.13; extra == 'torch'
Requires-Dist: torch>=2.2; extra == 'torch'
